solarcheck_ardexa.py
solarcheck_ardexa-1.3.0.dist-info/DESCRIPTION.rst
solarcheck_ardexa-1.3.0.dist-info/METADATA
solarcheck_ardexa-1.3.0.dist-info/RECORD
solarcheck_ardexa-1.3.0.dist-info/WHEEL
solarcheck_ardexa-1.3.0.dist-info/entry_points.txt
solarcheck_ardexa-1.3.0.dist-info/metadata.json
solarcheck_ardexa-1.3.0.dist-info/top_level.txt
