Metadata-Version: 2.0
Name: solarcheck-ardexa
Version: 1.3.0
Summary: Collect from Phoenix Contact SOLARCHECK String Monitor and send the data to your cloud using Ardexa
Home-page: https://github.com/ardexa/solarcheck-strings
Author: Ardexa Pty Limited
Author-email: support@ardexa.com
License: UNKNOWN
Project-URL: Source, https://github.com/ardexa/solarcheck-strings/
Project-URL: Bug Reports, https://github.com/ardexa/solarcheck-strings/issues
Keywords: Phoenix Contact SOLARCHECK solar string monitor ardexa
Platform: UNKNOWN
Classifier: License :: OSI Approved :: MIT License
Classifier: Programming Language :: Python :: 2
Classifier: Programming Language :: Python :: 2.7
Classifier: Programming Language :: Python :: 3
Classifier: Programming Language :: Python :: 3.4
Classifier: Programming Language :: Python :: 3.5
Classifier: Programming Language :: Python :: 3.6
Requires-Python: >=2.7
Requires-Dist: future
Requires-Dist: ardexaplugin
Requires-Dist: Click
